transcoder.py
ptpl_transcoder-1.0.1.dist-info/METADATA
ptpl_transcoder-1.0.1.dist-info/WHEEL
ptpl_transcoder-1.0.1.dist-info/entry_points.txt
ptpl_transcoder-1.0.1.dist-info/top_level.txt
ptpl_transcoder-1.0.1.dist-info/RECORD
