Metadata-Version: 2.1
Name: ptpl-transcoder
Version: 1.0.1
Summary: A CLI tool to to decode .ptpl files into .xml and encode .xml files back into .ptpl format.
Home-page: https://github.com/KRWCLASSIC/PTPL-CLI-Transcoder
Author: KRW CLASSIC
Author-email: KRW CLASSIC <classic.krw@gmail.com>
Project-URL: Source, https://github.com/KRWCLASSIC/PTPL-CLI-Transcoder
Project-URL: Tracker, https://github.com/KRWCLASSIC/PTPL-CLI-Transcoder/issues
Requires-Dist: lxml
